itk/MorphologicalContourInterpolationPython.py
itk/_MorphologicalContourInterpolationPython.pyd
itk/__init_morphologicalcontourinterpolation__.py
itk/itkMorphologicalContourInterpolatorPython.py
itk/Configuration/MorphologicalContourInterpolationConfig.py
itk/Configuration/MorphologicalContourInterpolation_snake_case.py
itk_morphologicalcontourinterpolation-2.1.2.dist-info/licenses/LICENSE
itk_morphologicalcontourinterpolation.libs/msvcp140.dll
itk_morphologicalcontourinterpolation.libs/tbb12.dll
itk_morphologicalcontourinterpolation-2.1.2.dist-info/DELVEWHEEL
itk_morphologicalcontourinterpolation-2.1.2.dist-info/METADATA
itk_morphologicalcontourinterpolation-2.1.2.dist-info/WHEEL
itk_morphologicalcontourinterpolation-2.1.2.dist-info/RECORD
