Metadata-Version: 2.1
Name: itk-morphologicalcontourinterpolation
Version: 2.1.2
Summary: A morphology-based approach for interslice interpolation of anatomical slices from volumetric images.
Keywords: itk,InsightToolkit
Author-Email: =?utf-8?b?RMW+ZW5hbiBadWtpxIc=?= <community@itk.org>, Matt McCormick <matt@mmmccormick.com>
License:                                  Apache License
Classifier: Development Status :: 4 - Beta
Classifier: Intended Audience :: Developers
Classifier: Intended Audience :: Education
Classifier: Intended Audience :: Healthcare Industry
Classifier: Intended Audience :: Science/Research
Classifier: License :: OSI Approved :: Apache Software License
Classifier: Operating System :: MacOS
Classifier: Operating System :: Microsoft :: Windows
Classifier: Operating System :: POSIX
Classifier: Operating System :: Unix
Classifier: Programming Language :: C++
Classifier: Programming Language :: Python
Classifier: Topic :: Scientific/Engineering
Classifier: Topic :: Scientific/Engineering :: Information Analysis
Classifier: Topic :: Scientific/Engineering :: Medical Science Apps.
Classifier: Topic :: Software Development :: Libraries
Project-URL: Download, https://github.com/KitwareMedical/ITKContourInterpolation
Project-URL: Homepage, https://github.com/KitwareMedical/ITKContourInterpolation
Requires-Python: >=3.9
Requires-Dist: itk==5.4.*
